{
 "pagenumber":'[ 20, 20, 20, 20, 20, 20, 20, 20, 20, 20, 20, 20, 20, 20, 20, 20, 20, 20, 20, 20, 20, 20, 20, 20, 20, 20, 20, 20, 20, 20, 20, 20, 20, 20, 20, 20, 20 ]',
"movieinfo":'[ "호러 / 131분 / 2016.06.09개봉", "호러 / 131분 / 2016.06.09개봉", "호러 / 131분 / 2016.06.09개봉", "호러 / 131분 / 2016.06.09개봉", "호러 / 131분 / 2016.06.09개봉", "호러 / 131분 / 2016.06.09개봉", "로맨스 / 110분 / 2016.06.01개봉", "로맨스 / 110분 / 2016.06.01개봉", "로맨스 / 110분 / 2016.06.01개봉", "로맨스 / 110분 / 2016.06.01개봉", "드라마 / 97분 / 2016.06.09개봉", "드라마 / 97분 / 2016.06.09개봉", "드라마,<U+00A0>어드벤처 / 106분 / 2016.06.09개봉", "드라마,<U+00A0>어드벤처 / 106분 / 2016.06.09개봉", "드라마,<U+00A0>어드벤처 / 106분 / 2016.06.09개봉", "드라마,<U+00A0>어드벤처 / 106분 / 2016.06.09개봉", "드라마,<U+00A0>어드벤처 / 106분 / 2016.06.09개봉", "드라마,<U+00A0>어드벤처 / 106분 / 2016.06.09개봉", "드라마,<U+00A0>어드벤처 / 106분 / 2016.06.09개봉", "미스터리,<U+00A0>스릴러,<U+00A0>드라마 / 156분 / 2016.05.11개봉", "미스터리,<U+00A0>스릴러,<U+00A0>드라마 / 156분 / 2016.05.11개봉", "드라마,<U+00A0>스릴러 / 145분 / 2016.06.01개봉", "드라마,<U+00A0>스릴러 / 145분 / 2016.06.01개봉", "드라마,<U+00A0>스릴러 / 145분 / 2016.06.01개봉", "드라마,<U+00A0>스릴러 / 145분 / 2016.06.01개봉", "드라마,<U+00A0>스릴러 / 145분 / 2016.06.01개봉", "액션,<U+00A0>어드벤처,<U+00A0>환타지 / 123분 / 2016.06.09개봉", "액션,<U+00A0>어드벤처,<U+00A0>환타지 / 123분 / 2016.06.09개봉", "액션,<U+00A0>어드벤처,<U+00A0>환타지 / 123분 / 2016.06.09개봉", "액션,<U+00A0>어드벤처,<U+00A0>환타지 / 123분 / 2016.06.09개봉", "액션,<U+00A0>어드벤처,<U+00A0>환타지 / 123분 / 2016.06.09개봉", "액션,<U+00A0>어드벤처,<U+00A0>환타지 / 123분 / 2016.06.09개봉", "드라마,<U+00A0>뮤지컬,<U+00A0>로맨스,<U+00A0>멜로 / 105분 / 2016.05.19개봉", "드라마,<U+00A0>뮤지컬,<U+00A0>로맨스,<U+00A0>멜로 / 105분 / 2016.05.19개봉", "액션,<U+00A0>어드벤처,<U+00A0>환타지,<U+00A0>SF / 145분 / 2016.05.25개봉", "액션,<U+00A0>어드벤처,<U+00A0>환타지,<U+00A0>SF / 145분 / 2016.05.25개봉", "애니메이션 / 131분 / 2016.06.09개봉" ]',
"showing":'[ "상영중", "상영중", "상영중", "상영중", "상영중", "상영중", "상영중", "상영중", "상영중", "상영중", "상영중", "상영중", "상영중", "상영중", "상영중", "상영중", "상영중", "상영중", "상영중", "상영중", "상영중", "상영중", "상영중", "상영중", "상영중", "상영중", "상영중", "상영중", "상영중", "상영중", "상영중", "상영중", "상영중", "상영중", "상영중", "상영중", "상영중" ]',
"grade":'[ "15세이상", "15세이상", "15세이상", "15세이상", "15세이상", "15세이상", "12세이상", "12세이상", "12세이상", "12세이상", "청소년관람불가", "청소년관람불가", "12세이상", "12세이상", "12세이상", "12세이상", "12세이상", "12세이상", "12세이상", "15세이상", "15세이상", "청소년관람불가", "청소년관람불가", "청소년관람불가", "청소년관람불가", "청소년관람불가", "12세이상", "12세이상", "12세이상", "12세이상", "12세이상", "12세이상", "15세이상", "15세이상", "12세이상", "12세이상", "전체" ]',
"title":'[ "컨저링2", "컨저링2", "컨저링2", "컨저링2", "컨저링2", "컨저링2", "미 비포 유", "미 비포 유", "미 비포 유", "미 비포 유", "본 투 비 블루", "본 투 비 블루", "정글북", "정글북", "정글북", "정글북", "정글북", "정글북", "정글북", "곡성(哭聲)", "곡성(哭聲)", "아가씨", "아가씨", "아가씨", "아가씨", "아가씨", "워크래프트: 전쟁의 서막", "워크래프트: 전쟁의 서막", "워크래프트: 전쟁의 서막", "워크래프트: 전쟁의 서막", "워크래프트: 전쟁의 서막", "워크래프트: 전쟁의 서막", "싱 스트리트", "싱 스트리트", "엑스맨: 아포칼립스", "엑스맨: 아포칼립스", "극장판 유희왕 더 다크 사이드 오브 디멘션즈" ]',
"timetable1":'[ "14:20잔여좌석175석, 상영관: /2D/2관5층/207석", "17:10잔여좌석181석, 상영관: /2D/2관5층/207석", "19:50잔여좌석171석, 상영관: /2D/2관5층/207석", "22:30잔여좌석179석, 상영관: /2D/2관5층/207석", "18:30잔여좌석106석, 상영관: /2D/5관5층/130석", "23:40잔여좌석112석, 상영관: /2D/5관5층/130석", "16:50잔여좌석74석, 상영관: /2D/9관3층/87석", "19:10잔여좌석64석, 상영관: /2D/9관3층/87석", "21:30잔여좌석76석, 상영관: /2D/9관3층/87석", "23:50잔여좌석76석, 상영관: /2D/9관3층/87석", "18:00잔여좌석102석, 상영관: /2D/8관3층/115석", "22:20잔여좌석102석, 상영관: /2D/8관3층/115석", "14:40잔여좌석82석, 상영관: /2D(자막)/4관5층/177석", "17:00잔여좌석156석, 상영관: /2D(자막)/4관5층/177석", "19:20잔여좌석144석, 상영관: /2D(자막)/4관5층/177석", "21:40잔여좌석155석, 상영관: /2D(자막)/4관5층/177석", "24:00잔여좌석158석, 상영관: /2D(자막)/4관5층/177석", "18:10잔여좌석114석, 상영관: /3D(자막)/1관5층/130석", "20:30잔여좌석118석, 상영관: /3D(자막)/1관5층/130석", "15:00잔여좌석114석, 상영관: /2D/1관5층/130석", "22:50잔여좌석115석, 상영관: /2D/1관5층/130석", "14:50잔여좌석166석, 상영관: /2D/3관5층/193석", "17:40잔여좌석171석, 상영관: /2D/3관5층/193석", "20:40잔여좌석169석, 상영관: /2D/3관5층/193석", "23:30잔여좌석174석, 상영관: /2D/3관5층/193석", "19:00잔여좌석73석, 상영관: /2D/6관3층/113석", "16:00잔여좌석116석, 상영관: /2D/5관5층/130석", "21:10잔여좌석116석, 상영관: /2D/5관5층/130석", "14:45잔여좌석150석, 상영관: /2D/7관3층/173석", "17:20잔여좌석154석, 상영관: /2D/7관3층/173석", "20:00잔여좌석146석, 상영관: /2D/7관3층/173석", "22:40잔여좌석154석, 상영관: /2D/7관3층/173석", "15:50잔여좌석99석, 상영관: /2D/8관3층/115석", "20:10잔여좌석94석, 상영관: /2D/8관3층/115석", "16:10잔여좌석101석, 상영관: /2D/6관3층/113석", "22:00잔여좌석101석, 상영관: /2D/6관3층/113석", "14:10잔여좌석76석, 상영관: /2D(더빙)/9관3층/87석" ]' 
}
